Metadata-Version: 2.1
Name: lubricate
Version: 0.1.0
Summary: # lubricate
